[
  {
    "_id": "576b7576a668c8e5087f182a",
    "index": 0,
    "guid": "161ff6ab-8188-4cfb-bb30-d53681189811",
    "isActive": false,
    "balance": "$2,617.06",
    "picture": "http://placehold.it/32x32",
    "age": 30,
    "eyeColor": "blue",
    "name": "Rodgers Puckett",
    "gender": "male",
    "company": "INSOURCE",
    "email": "rodgerspuckett@insource.com",
    "phone": "+1 (942) 486-3324",
    "address": "931 Highland Place, Dixie, Massachusetts, 8312",
    "about": "Laborum deserunt ex ut culpa pariatur voluptate ipsum ipsum minim id elit. Consequat laboris excepteur magna dolore laboris commodo magna fugiat ex consequat duis cupidatat. Ipsum consequat ut esse qui sunt officia do occaecat. Deserunt sit est laboris nostrud nisi reprehenderit cupidatat amet non. Sunt nisi quis esse commodo fugiat velit ut sunt minim id.\r\n",
    "registered": "2015-11-28",
    "latitude": -87.352156,
    "longitude": -27.445446,
    "tags": [
      "dolor",
      "magna",
      "amet",
      "Lorem",
      "ut",
      "proident",
      "officia"
    ],
    "friends": [
      {
        "id": 0,
        "name": "Parsons Talley"
      },
      {
        "id": 1,
        "name": "Loretta Jacobs"
      },
      {
        "id": 2,
        "name": "Villarreal Welch"
      }
    ],
    "greeting": "Hello, Rodgers Puckett! You have 10 unread messages.",
    "favoriteFruit": "banana"
  },
  {
    "_id": "576b75766f3ad2c47ccf6745",
    "index": 1,
    "guid": "1126554c-5f50-4482-95c6-4e28e51dfc9d",
    "isActive": false,
    "balance": "$3,190.48",
    "picture": "http://placehold.it/32x32",
    "age": 34,
    "eyeColor": "blue",
    "name": "Brenda Alvarez",
    "gender": "female",
    "company": "ACUSAGE",
    "email": "brendaalvarez@acusage.com",
    "phone": "+1 (938) 424-2506",
    "address": "329 Richards Street, Stockdale, Utah, 5112",
    "about": "Tempor id veniam anim ullamco esse ut duis in proident dolor cupidatat ut. Sint minim deserunt qui cillum ad laborum id. Minim exercitation ea do minim culpa eu adipisicing aliqua nisi duis non.\r\n",
    "registered": "2014-04-29",
    "latitude": -56.935078,
    "longitude": 137.504203,
    "tags": [
      "fugiat",
      "occaecat",
      "mollit",
      "quis",
      "consequat",
      "dolor",
      "incididunt"
    ],
    "friends": [
      {
        "id": 0,
        "name": "Harper Collier"
      },
      {
        "id": 1,
        "name": "Ramona Warner"
      },
      {
        "id": 2,
        "name": "Murray Roach"
      }
    ],
    "greeting": "Hello, Brenda Alvarez! You have 10 unread messages.",
    "favoriteFruit": "apple"
  },
  {
    "_id": "576b7576660ca3d8303c0346",
    "index": 2,
    "guid": "87850886-ac06-4a19-a703-120bd149eab8",
    "isActive": false,
    "balance": "$3,401.08",
    "picture": "http://placehold.it/32x32",
    "age": 29,
    "eyeColor": "green",
    "name": "Bernadine Dale",
    "gender": "female",
    "company": "GENMEX",
    "email": "bernadinedale@genmex.com",
    "phone": "+1 (893) 441-3088",
    "address": "137 Hale Avenue, Albany, New Jersey, 1721",
    "about": "Cillum et nulla dolor aliquip aliquip amet sint. Reprehenderit cupidatat irure incididunt eu fugiat irure proident ex. Eiusmod occaecat aute deserunt exercitation incididunt laboris in velit nulla proident nostrud enim. Excepteur tempor exercitation ullamco reprehenderit voluptate cupidatat nulla aliqua occaecat aute amet ea nisi. Et nulla nisi est culpa est duis cillum. Do esse amet officia magna anim cupidatat velit exercitation fugiat ipsum magna.\r\n",
    "registered": "2015-05-07",
    "latitude": 19.095669,
    "longitude": 92.051129,
    "tags": [
      "duis",
      "irure",
      "consequat",
      "consequat",
      "tempor",
      "ipsum",
      "nisi"
    ],
    "friends": [
      {
        "id": 0,
        "name": "Juanita Horne"
      },
      {
        "id": 1,
        "name": "Berger Gilliam"
      },
      {
        "id": 2,
        "name": "Cleveland Morales"
      }
    ],
    "greeting": "Hello, Bernadine Dale! You have 3 unread messages.",
    "favoriteFruit": "banana"
  },
  {
    "_id": "576b75762a7bde84ed958227",
    "index": 3,
    "guid": "3f3a40eb-a152-4373-8880-da9a2a08db3d",
    "isActive": false,
    "balance": "$3,386.92",
    "picture": "http://placehold.it/32x32",
    "age": 29,
    "eyeColor": "green",
    "name": "Jayne Blackwell",
    "gender": "female",
    "company": "QUALITEX",
    "email": "jayneblackwell@qualitex.com",
    "phone": "+1 (993) 422-3847",
    "address": "930 Anthony Street, Calverton, South Carolina, 5948",
    "about": "Ea reprehenderit enim Lorem deserunt dolor pariatur est. Ad sunt ipsum excepteur sit do qui cupidatat anim aliquip esse minim. Sunt anim incididunt tempor occaecat anim eu ad cupidatat sit labore exercitation. Consequat eu qui esse magna eiusmod culpa eu eiusmod excepteur tempor quis.\r\n",
    "registered": "2015-07-10",
    "latitude": -86.410102,
    "longitude": 88.402588,
    "tags": [
      "excepteur",
      "pariatur",
      "deserunt",
      "id",
      "duis",
      "Lorem",
      "consectetur"
    ],
    "friends": [
      {
        "id": 0,
        "name": "Whitfield Wilkinson"
      },
      {
        "id": 1,
        "name": "Boyd Zamora"
      },
      {
        "id": 2,
        "name": "Benton Baker"
      }
    ],
    "greeting": "Hello, Jayne Blackwell! You have 7 unread messages.",
    "favoriteFruit": "banana"
  },
  {
    "_id": "576b757620ca3ccdd0ccb16f",
    "index": 4,
    "guid": "19a683e5-b0b3-4eae-801e-693d8715f99c",
    "isActive": true,
    "balance": "$1,515.77",
    "picture": "http://placehold.it/32x32",
    "age": 40,
    "eyeColor": "green",
    "name": "Williamson Banks",
    "gender": "male",
    "company": "SKYBOLD",
    "email": "williamsonbanks@skybold.com",
    "phone": "+1 (883) 577-3674",
    "address": "552 Tennis Court, Trail, Michigan, 5286",
    "about": "Fugiat commodo eu voluptate non velit velit labore nisi officia anim. Aliqua sit anim tempor aliquip. Sunt laboris culpa culpa mollit Lorem magna cupidatat sint tempor. Deserunt nulla dolor incididunt sit sint in laborum esse labore aute occaecat nisi. Nulla est aliqua dolor cupidatat aute et.\r\n",
    "registered": "2014-07-08",
    "latitude": -60.007319,
    "longitude": -63.482666,
    "tags": [
      "incididunt",
      "veniam",
      "dolor",
      "ad",
      "dolore",
      "duis",
      "cillum"
    ],
    "friends": [
      {
        "id": 0,
        "name": "Hart Petersen"
      },
      {
        "id": 1,
        "name": "Winnie Ingram"
      },
      {
        "id": 2,
        "name": "Claudine Rush"
      }
    ],
    "greeting": "Hello, Williamson Banks! You have 9 unread messages.",
    "favoriteFruit": "strawberry"
  },
  {
    "_id": "576b75768bae1e20ffbd03bf",
    "index": 5,
    "guid": "211027d4-3c2c-4225-a0be-5d122e1680d1",
    "isActive": true,
    "balance": "$2,507.09",
    "picture": "http://placehold.it/32x32",
    "age": 32,
    "eyeColor": "blue",
    "name": "Joyner Wilder",
    "gender": "male",
    "company": "ZENSUS",
    "email": "joynerwilder@zensus.com",
    "phone": "+1 (801) 478-2780",
    "address": "187 Wyona Street, Templeton, Virgin Islands, 3063",
    "about": "Magna laborum nostrud nostrud minim voluptate laboris ea qui mollit in occaecat. Sunt laborum cillum amet ipsum dolore. Deserunt dolore aliqua laborum ex sint commodo. Culpa commodo labore in anim excepteur. Elit non id deserunt do deserunt veniam excepteur cillum elit.\r\n",
    "registered": "2016-01-02",
    "latitude": 7.385393,
    "longitude": 84.396849,
    "tags": [
      "occaecat",
      "magna",
      "est",
      "consectetur",
      "tempor",
      "excepteur",
      "mollit"
    ],
    "friends": [
      {
        "id": 0,
        "name": "Peck Allen"
      },
      {
        "id": 1,
        "name": "Wade Heath"
      },
      {
        "id": 2,
        "name": "Rosella Wise"
      }
    ],
    "greeting": "Hello, Joyner Wilder! You have 7 unread messages.",
    "favoriteFruit": "apple"
  }
]